[
  {
    "inputs": [
      {
        "internalType": "address",
        "name": "_collectionContract",
        "type": "address"
      },
      {
        "internalType": "address",
        "name": "_accessControlContract",
        "type": "address"
      },
      { "internalType": "address", "name": "_NFTContract", "type": "address" },
      { "internalType": "string", "name": "_symbol", "type": "string" },
      { "internalType": "string", "name": "_name", "type": "string" }
    ],
    "stateMutability": "nonpayable",
    "type": "constructor"
  },
  {
    "anonymous": false,
    "inputs": [
      {
        "indexed": true,
        "internalType": "address",
        "name": "oldAccessControl",
        "type": "address"
      },
      {
        "indexed": true,
        "internalType": "address",
        "name": "newAccessControl",
        "type": "address"
      },
      {
        "indexed": false,
        "internalType": "address",
        "name": "updater",
        "type": "address"
      }
    ],
    "name": "AccessControlUpdated",
    "type": "event"
  },
  {
    "anonymous": false,
    "inputs": [
      {
        "indexed": true,
        "internalType": "address",
        "name": "oldChromadinCollection",
        "type": "address"
      },
      {
        "indexed": true,
        "internalType": "address",
        "name": "newChromadinCollection",
        "type": "address"
      },
      {
        "indexed": false,
        "internalType": "address",
        "name": "updater",
        "type": "address"
      }
    ],
    "name": "ChromadinCollectionUpdated",
    "type": "event"
  },
  {
    "anonymous": false,
    "inputs": [
      {
        "indexed": true,
        "internalType": "address",
        "name": "oldChromadinEscrow",
        "type": "address"
      },
      {
        "indexed": true,
        "internalType": "address",
        "name": "newChromadinEscrow",
        "type": "address"
      },
      {
        "indexed": false,
        "internalType": "address",
        "name": "updater",
        "type": "address"
      }
    ],
    "name": "ChromadinEscrowUpdated",
    "type": "event"
  },
  {
    "anonymous": false,
    "inputs": [
      {
        "indexed": true,
        "internalType": "address",
        "name": "oldChromadinNFT",
        "type": "address"
      },
      {
        "indexed": true,
        "internalType": "address",
        "name": "newChromadinNFT",
        "type": "address"
      },
      {
        "indexed": false,
        "internalType": "address",
        "name": "updater",
        "type": "address"
      }
    ],
    "name": "ChromadinNFTUpdated",
    "type": "event"
  },
  {
    "anonymous": false,
    "inputs": [
      {
        "indexed": false,
        "internalType": "uint256[]",
        "name": "tokenIds",
        "type": "uint256[]"
      },
      {
        "indexed": false,
        "internalType": "uint256",
        "name": "totalPrice",
        "type": "uint256"
      },
      {
        "indexed": false,
        "internalType": "address",
        "name": "buyer",
        "type": "address"
      }
    ],
    "name": "TokensBought",
    "type": "event"
  },
  {
    "inputs": [],
    "name": "accessControl",
    "outputs": [
      {
        "internalType": "contract AccessControl",
        "name": "",
        "type": "address"
      }
    ],
    "stateMutability": "view",
    "type": "function"
  },
  {
    "inputs": [
      { "internalType": "uint256[]", "name": "_tokenIds", "type": "uint256[]" },
      {
        "internalType": "address",
        "name": "_chosenTokenAddress",
        "type": "address"
      }
    ],
    "name": "buyTokens",
    "outputs": [],
    "stateMutability": "nonpayable",
    "type": "function"
  },
  {
    "inputs": [],
    "name": "chromadinCollection",
    "outputs": [
      {
        "internalType": "contract ChromadinCollection",
        "name": "",
        "type": "address"
      }
    ],
    "stateMutability": "view",
    "type": "function"
  },
  {
    "inputs": [],
    "name": "chromadinEscrow",
    "outputs": [
      {
        "internalType": "contract ChromadinEscrow",
        "name": "",
        "type": "address"
      }
    ],
    "stateMutability": "view",
    "type": "function"
  },
  {
    "inputs": [],
    "name": "chromadinNFT",
    "outputs": [
      { "internalType": "contract ChromadinNFT", "name": "", "type": "address" }
    ],
    "stateMutability": "view",
    "type": "function"
  },
  {
    "inputs": [
      { "internalType": "uint256", "name": "_collectionId", "type": "uint256" }
    ],
    "name": "getCollectionSoldCount",
    "outputs": [{ "internalType": "uint256", "name": "", "type": "uint256" }],
    "stateMutability": "view",
    "type": "function"
  },
  {
    "inputs": [
      { "internalType": "uint256", "name": "_collectionId", "type": "uint256" }
    ],
    "name": "getTokensSoldCollection",
    "outputs": [
      { "internalType": "uint256[]", "name": "", "type": "uint256[]" }
    ],
    "stateMutability": "view",
    "type": "function"
  },
  {
    "inputs": [],
    "name": "name",
    "outputs": [{ "internalType": "string", "name": "", "type": "string" }],
    "stateMutability": "view",
    "type": "function"
  },
  {
    "inputs": [
      {
        "internalType": "address",
        "name": "_newChromadinEscrowAddress",
        "type": "address"
      }
    ],
    "name": "setChromadinEscrow",
    "outputs": [],
    "stateMutability": "nonpayable",
    "type": "function"
  },
  {
    "inputs": [],
    "name": "symbol",
    "outputs": [{ "internalType": "string", "name": "", "type": "string" }],
    "stateMutability": "view",
    "type": "function"
  },
  {
    "inputs": [
      {
        "internalType": "address",
        "name": "_newAccessControlAddress",
        "type": "address"
      }
    ],
    "name": "updateAccessControl",
    "outputs": [],
    "stateMutability": "nonpayable",
    "type": "function"
  },
  {
    "inputs": [
      {
        "internalType": "address",
        "name": "_newChromadinCollectionAddress",
        "type": "address"
      }
    ],
    "name": "updateChromadinCollection",
    "outputs": [],
    "stateMutability": "nonpayable",
    "type": "function"
  },
  {
    "inputs": [
      {
        "internalType": "address",
        "name": "_newChromadinNFTAddress",
        "type": "address"
      }
    ],
    "name": "updateChromadinNFT",
    "outputs": [],
    "stateMutability": "nonpayable",
    "type": "function"
  }
]
